README.md
setup.py
frasco_models/__init__.py
frasco_models/backend.py
frasco_models/bs_form_template.html
frasco_models/form_template.html
frasco_models/query.py
frasco_models/transaction.py
frasco_models/utils.py
frasco_models.egg-info/PKG-INFO
frasco_models.egg-info/SOURCES.txt
frasco_models.egg-info/dependency_links.txt
frasco_models.egg-info/not-zip-safe
frasco_models.egg-info/requires.txt
frasco_models.egg-info/top_level.txt
frasco_models/admin/__init__.py
frasco_models/admin/templates/admin/models_default/create.html
frasco_models/admin/templates/admin/models_default/edit.html
frasco_models/admin/templates/admin/models_default/index.html
frasco_models/backends/__init__.py
frasco_models/backends/mongoengine.py
frasco_models/backends/sqlalchemy.py
frasco_models/form/__init__.py
frasco_models/form/fields.py