Metadata-Version: 1.0
Name: frasco-models
Version: 0.7.0
Summary: ORM for Frasco
Home-page: http://github.com/frascoweb/frasco-models
Author: Maxime Bouroumeau-Fuseau
Author-email: maxime.bouroumeau@gmail.com
License: MIT
Platform: any
